database/__init__.py
database/database.py
sqlHelper-1.1.8.dist-info/METADATA
sqlHelper-1.1.8.dist-info/WHEEL
sqlHelper-1.1.8.dist-info/top_level.txt
sqlHelper-1.1.8.dist-info/RECORD
